emonpy/__init__.py
emonpy/connection.py
emonpy/const.py
emonpy/emon.py
emonpy/sensor.py
emonpy-0.0.4.dist-info/LICENSE
emonpy-0.0.4.dist-info/METADATA
emonpy-0.0.4.dist-info/WHEEL
emonpy-0.0.4.dist-info/top_level.txt
emonpy-0.0.4.dist-info/RECORD
